MANIFEST.in
README.md
setup.py
aadiscordbot/__init__.py
aadiscordbot/admin.py
aadiscordbot/app_settings.py
aadiscordbot/apps.py
aadiscordbot/auth_hooks.py
aadiscordbot/bot.py
aadiscordbot/bot_tasks.py
aadiscordbot/launcher.py
aadiscordbot/models.py
aadiscordbot/providers.py
aadiscordbot/tasks.py
aadiscordbot/urls.py
aadiscordbot/views.py
aadiscordbot/cogs/__init__.py
aadiscordbot/cogs/about.py
aadiscordbot/cogs/abuse.py
aadiscordbot/cogs/admin.py
aadiscordbot/cogs/auth.py
aadiscordbot/cogs/eastereggs.py
aadiscordbot/cogs/eightball.py
aadiscordbot/cogs/facwar.py
aadiscordbot/cogs/members.py
aadiscordbot/cogs/models.py
aadiscordbot/cogs/price_check.py
aadiscordbot/cogs/prom_export.py
aadiscordbot/cogs/quote.py
aadiscordbot/cogs/reaction_roles.py
aadiscordbot/cogs/remind.py
aadiscordbot/cogs/services.py
aadiscordbot/cogs/sov.py
aadiscordbot/cogs/tickets.py
aadiscordbot/cogs/time.py
aadiscordbot/cogs/timers.py
aadiscordbot/cogs/welcomegoodbye.py
aadiscordbot/cogs/utils/__init__.py
aadiscordbot/cogs/utils/context.py
aadiscordbot/cogs/utils/decorators.py
aadiscordbot/cogs/utils/exceptions.py
aadiscordbot/migrations/0001_initial.py
aadiscordbot/migrations/0002_reactionrolebinding_reactionrolemessage.py
aadiscordbot/migrations/0003_authbotconfiguration.py
aadiscordbot/migrations/0004_settings.py
aadiscordbot/migrations/0005_rr_fixes_blank_admins.py
aadiscordbot/migrations/0006_goodbyemessage_welcomemessage.py
aadiscordbot/migrations/0007_quotemessage.py
aadiscordbot/migrations/0008_channels_deleted.py
aadiscordbot/migrations/0009_alter_quotemessage_options.py
aadiscordbot/migrations/0010_alter_discordbot_options_ticketgroups.py
aadiscordbot/migrations/0011_alter_ticketgroups_options_and_more.py
aadiscordbot/migrations/__init__.py
pns_allianceauth_discordbot.egg-info/PKG-INFO
pns_allianceauth_discordbot.egg-info/SOURCES.txt
pns_allianceauth_discordbot.egg-info/dependency_links.txt
pns_allianceauth_discordbot.egg-info/requires.txt
pns_allianceauth_discordbot.egg-info/top_level.txt